protocol/__init__.py
protocol/com_address.py
protocol/content_payload.py
protocol/driver_type.py
protocol/ejector_data.py
protocol/empty_payload.py
protocol/function_id.py
protocol/io_address.py
protocol/io_address_array.py
protocol/io_operation.py
protocol/io_operation_batch.py
protocol/io_status.py
protocol/io_status_batch.py
protocol/meta_info.py
protocol/motor_basic_info.py
protocol/motor_control_operation.py
protocol/motor_direction.py
protocol/motor_operation.py
protocol/motor_speed.py
protocol/motor_stats.py
protocol/read_trigger_count.py
protocol/request.py
protocol/response.py
protocol/sensor_data.py
protocol/sensor_query_interval.py
protocol/serial_number.py
protocol/trigger_start_position.py
protocol/unix_time_stamp.py
mcu_communication-1.0.0.dist-info/METADATA
mcu_communication-1.0.0.dist-info/WHEEL
mcu_communication-1.0.0.dist-info/top_level.txt
mcu_communication-1.0.0.dist-info/RECORD
